Workbook

Sheet Index
B1: P&L Model using Training Dataset
B2: Sheet index
B4: Sheet No | C4: Worksheet | D4: Notes
B5: 1 | C5: Index
B6: 2 | C6: 1. P&L extractions -->
B7: 3 | C7: 1.1 FY2024
B8: 4 | C8: 1.2 FY2025
B9: 5 | C9: 1.3 FY2026
B10: 6 | C10: 2. Functions -->
B11: 7 | C11: 2.1 Database
B12: 8 | C12: 2.2 P&L statement
B13: 19 | C13: 3. Charts
B14: 20 | C14: 3.1 Column Chart
B15: 21 | C15: 3.2 Line chart
B16: 22 | C16: 3.3 Stacked Column chart

Sheet 1.1 FY2024
B1: FY2024
B4: Code | C4: P&L account | D4: Partner company | E4: Name of partner company | F4: Amounts | G4: Account number
B5: 2001110000111111 | C5: Core business revenues | D5: 111111 | E5: External | F5: -14500341 | G5: 2001110000
B6: 2001190000111111 | C6: Other revenues | D6: 111111 | E6: External | F6: -4794856.2 | G6: 2001190000
B7: 20200000001009 | C7: Capitalized costs | D7: 1009 | E7: Green Ventures Ltd | F7: -154890.4 | G7: 2020000000
B8: 20200000001007 | C8: Capitalized costs | D8: 1007 | E8: Generco Sunshine JSC | F8: -1180894.1 | G8: 2020000000
B9: 20200000001008 | C9: Capitalized costs | D9: 1008 | E9: Greenco Ltd | F9: -793079.51 | G9: 2020000000
B10: 2020000000111101 | C10: Capitalized costs | D10: 111101 | E10: Not assigned | F10: -2277197.6 | G10: 2020000000
B11: 2021900000111111 | C11: Direct costs | D11: 111111 | E11: External | F11: 4428911.8 | G11: 2021900000
B12: 2024080000111111 | C12: Freight outbound expenses | D12: 111111 | E12: External | F12: 16977.628 | G12: 2024080000
B13: 202409000088 | C13: R&D expenses | D13: 88 | E13: Generco Ltd | F13: 2245437.5 | G13: 2024090000
B14: 2024090000111111 | C14: R&D expenses | D14: 111111 | E14: External | F14: 16605.634 | G14: 2024090000
B15: 2041000000111111 | C15: Wages and salaries | D15: 111111 | E15: External | F15: 4683394 | G15: 2041000000
B16: 2042000000111101 | C16: Pension contributions | D16: 111101 | E16: Not assigned | F16: 1143051.6 | G16: 2042000000
... B20: 20512100001 | C20: D&A | D20: 1 | E20: Not assigned | F20: 41981.296 | G20: 2051210000
B21: 20690100001 | C21: Corporate recharges | D21: 1 | E21: Greeny Ltd | F21: -2156147.4 | G21: 2069010000
B22: 206901000014 | C22: Corporate recharges | D22: 14 | E22: Generco Cosmetics Ltd | F22: -291428.55 | G22: 2069010000
B23: 20690100001037 | C23: Corporate recharges | D23: 1037 | E23: Generco Canada JSC | F23: 0 | G23: 2069010000
B24: 20690100001087 | C24: Corporate recharges | D24: 1087 | E24: Gener Beauty GmbH | F24: -33736.5 | G24: 2069010000
B25: 20690100001009 | C25: Corporate recharges | D25: 1009 | E25: Green Ventures Ltd | F25: 0 | G25: 2069010000
B26: 20690100001007 | C26: Corporate recharges | D26: 1007 | E26: Generco Sunshine JSC | F26: 0 | G26: 2069010000
B27: 20690100001008 | C27: Corporate recharges | D27: 1008 | E27: Greenco Ltd | F27: 0 | G27: 2069010000
B28: 20690100001240 | C28: Corporate recharges | D28: 1240 | E28: Generco UK | F28: -199600.4 | G28: 2069010000
B29: 2069010000111111 | C29: Corporate recharges | D29: 111111 | E29: External | F29: -539141.4 | G29: 2069010000
B30: 2069980000111111 | C30: Other income | D30: 111111 | E30: External | F30: -57.222 | G30: 2069980000
B31: 2070400000111111 | C31: Marketing expenses | D31: 111111 | E31: External | F31: 22314.88 | G31: 2070400000
B32: 207050000088 | C32: Software&IT | D32: 88 | E32: Generco Ltd | F32: 204000 | G32: 2070500000
B33: 2070500000111111 | C33: Software&IT | D33: 111111 | E33: External | F33: 138.414 | G33: 2070500000
B34: 2070600000111111 | C34: Leasings | D34: 111111 | E34: External | F34: 1127445.9 | G34: 2070600000
B35: 207090000043 | C35: Service expenses | D35: 43 | E35: Greeny France SL | F35: 133722 | G35: 2070900000
B36: 20709000002240 | C36: Service expenses | D36: 2240 | E36: Greeny Germany GmbH | F36: 328061.89 | G36: 2070900000
B37: 2070900000111111 | C37: Service expenses | D37: 111111 | E37: External | F37: 2081304.3 | G37: 2070900000
B38: 2071000000111111 | C38: Charges and contributions | D38: 111111 | E38: External | F38: 33410.032 | G38: 2071000000
B39: 2071100000111111 | C39: Insurance expenses | D39: 111111 | E39: External | F39: 213090.85 | G39: 2071100000
B40: 2071209200111111 | C40: Travel expenses | D40: 111111 | E40: External | F40: 1813525 | G40: 2071209200
B41: 2071209400111111 | C41: Utility expenses | D41: 111111 | E41: External | F41: 5552.2 | G41: 2071209400
B42: 2071209500111111 | C42: Legal expenses | D42: 111111 | E42: External | F42: 43868.976 | G42: 2071209500
B43: 2071980000111101 | C43: Misc costs | D43: 111101 | E43: Not assigned | F43: 10934.672 | G43: 2071980000
B44: 2079022000111111 | C44: Consulting fees | D44: 111111 | E44: External | F44: 20400 | G44: 2079022000
B45: 2079070000105 | C45: Misc extraordinary expenses | D45: 105 | E45: Generco Healthcare Ltd | F45: 0 | G45: 2079070000
B46: 2079070000111111 | C46: Misc extraordinary expenses | D46: 111111 | E46: External | F46: 563918.15 | G46: 2079070000
B47: 20790800001009 | C47: Difference from eliminations | D47: 1009 | E47: Green Ventures Ltd | F47: 0 | G47: 2079080000
B48: 20790800001007 | C48: Difference from eliminations | D48: 1007 | E48: Generco Sunshine JSC | F48: 0 | G48: 2079080000
... B61: 2999999999111101 | C61: Net income/(loss) | D61: 111101 | E61: Not assigned | F61: -2904118 | G61: 2999999999

Sheet 1.2 FY2025
B1: FY2025
B4: Code | C4: P&L account | D4: Partner company | E4: Name of partner company | F4: Amounts | G4: Account number
B5: 2001110000105 | C5: Core business revenues | D5: 105 | E5: Generco Healthcare Ltd | F5: -355396.61 | G5: 2001110000
B6: 2001110000111111 | C6: Core business revenues | D6: 111111 | E6: External | F6: -15792899 | G6: 2001110000
B7: 2001190000111111 | C7: Other revenues | D7: 111111 | E7: External | F7: -6960217.6 | G7: 2001190000
B8: 20200000001086 | C8: Capitalized costs | D8: 1086 | E8: G&Resources Ltd | F8: -420017.15 | G8: 2020000000
B9: 20200000001007 | C9: Capitalized costs | D9: 1007 | E9: Generco Sunshine JSC | F9: -89234.88 | G9: 2020000000
B10: 20200000001008 | C10: Capitalized costs | D10: 1008 | E10: Greenco Ltd | F10: -26173 | G10: 2020000000
B11: 2020000000111101 | C11: Capitalized costs | D11: 111101 | E11: Not assigned | F11: -209401.92 | G11: 2020000000
B12: 2021210000111111 | C12: Utility charges | D12: 111111 | E12: External | F12: 14589.33 | G12: 2021210000
B13: 2021900000111111 | C13: Direct costs | D13: 111111 | E13: External | F13: 5463188.8 | G13: 2021900000
B14: 2024080000111111 | C14: Freight outbound expenses | D14: 111111 | E14: External | F14: 343675 | G14: 2024080000
B15: 202409000019 | C15: R&D expenses | D15: 19 | E15: Generco Cosmetics Ltd | F15: 38521 | G15: 2024090000
B16: 202409000088 | C16: R&D expenses | D16: 88 | E16: Generco Ltd | F16: 1980162.2 | G16: 2024090000
B17: 20240900001283 | C17: R&D expenses | D17: 1283 | E17: Generco Ventures Ltd | F17: 1820 | G17: 2024090000
B18: 20240900001924 | C18: R&D expenses | D18: 1924 | E18: Generco Infrastructure Ltd | F18: 10448.13 | G18: 2024090000
B19: 20240900002486 | C19: R&D expenses | D19: 2486 | E19: Generco Exloration Ltd | F19: 10412.5 | G19: 2024090000
B20: 2024090000111111 | C20: R&D expenses | D20: 111111 | E20: External | F20: 27148.625 | G20: 2024090000
B21: 2041000000111111 | C21: Wages and salaries | D21: 111111 | E21: External | F21: 5507141.1 | G21: 2041000000
B22: 2042000000111101 | C22: Social security payments | D22: 111101 | E22: Not assigned | F22: 1752994.2 | G22: 2042000000
B23: 2042000000111101 | C23: Pension contributions | D23: 111101 | E23: Not assigned | F23: 304303.86 | G23: 2042000000
B24: 2045000000111101 | C24: Severance indemnity contribution | D24: 111101 | E24: Not assigned | F24: 500500 | G24: 2045000000
B25: 2049000000111101 | C25: Other personnel expenses | D25: 111101 | E25: Not assigned | F25: 6919.85 | G25: 2049000000
B26: 2051210000111101 | C26: D&A | D26: 111101 | E26: Not assigned | F26: 1897676.9 | G26: 2051210000
B27: 2051260000111101 | C27: D&A | D27: 111101 | E27: Not assigned | F27: 146328.94 | G27: 2051260000
B28: 2060220000111111 | C28: Gains from disposal of PP&E | D28: 111111 | E28: External | F28: -121553.07 | G28: 2060220000
B29: 20690100001 | C29: Corporate recharges | D29: 1 | E29: Greeny Ltd | F29: -1643711.1 | G29: 2069010000
B30: 206901000019 | C30: Corporate recharges | D30: 19 | E30: Generco Cosmetics Ltd | F30: -416278.66 | G30: 2069010000
B31: 20690100001076 | C31: Corporate recharges | D31: 1076 | E31: Generco Trading Ltd | F31: -364243.84 | G31: 2069010000
B32: 20690100001086 | C32: Corporate recharges | D32: 1086 | E32: G&Resources Ltd | F32: 0 | G32: 2069010000
B33: 20690100001009 | C33: Corporate recharges | D33: 1009 | E33: Green Ventures Ltd | F33: 0 | G33: 2069010000
B34: 20690100001007 | C34: Corporate recharges | D34: 1007 | E34: Generco Sunshine JSC | F34: 0 | G34: 2069010000
B35: 20690100001008 | C35: Corporate recharges | D35: 1008 | E35: Greenco Ltd | F35: 0 | G35: 2069010000
B36: 20690100001240 | C36: Corporate recharges | D36: 1240 | E36: Generco UK | F36: -10461.36 | G36: 2069010000
B37: 20690100001007 | C37: Corporate recharges | D37: 1007 | E37: Generco Semiconductors Ltd | F37: 0 | G37: 2069010000
B38: 206901000047037 | C38: Corporate recharges | D38: 47037 | E38: G&CR Global Ltd | F38: -482611.04 | G38: 2069010000
B39: 2069010000111111 | C39: Corporate recharges | D39: 111111 | E39: External | F39: -6785.94 | G39: 2069010000
B40: 206998000088 | C40: Other income | D40: 88 | E40: Generco Ltd | F40: -2436.35 | G40: 2069980000
B41: 2069980000111111 | C41: Other income | D41: 111111 | E41: External | F41: 9793.84 | G41: 2069980000
B42: 2070290000111101 | C42: Concession fees other | D42: 111101 | E42: Not assigned | F42: 81.34 | G42: 2070290000
B43: 2070400000111111 | C43: Marketing expenses | D43: 111111 | E43: External | F43: 65947.7 | G43: 2070400000
B44: 2070500000111111 | C44: Software&IT | D44: 111111 | E44: External | F44: 5138.91 | G44: 2070500000
B45: 2070600000111111 | C45: Leasings | D45: 111111 | E45: External | F45: 1055381.5 | G45: 2070600000
B46: 20709000002240 | C46: Service expenses | D46: 2240 | E46: Greeny Germany GmbH | F46: 430845.34 | G46: 2070900000
B47: 2070900000105 | C47: Service expenses | D47: 105 | E47: Generco Healthcare Ltd | F47: 276920 | G47: 2070900000
B48: 2070900000111111 | C48: Service expenses | D48: 111111 | E48: External | F48: 1130021 | G48: 2070900000
B49: 2071000000111111 | C49: Charges and contributions | D49: 111111 | E49: External | F49: 7293.545 | G49: 2071000000
B50: 20711000001900 | C50: Insurance expenses | D50: 1900 | E50: Generco Metals Gm | F50: 0 | G50: 2071100000
B51: 2071100000111111 | C51: Insurance expenses | D51: 111111 | E51: External | F51: 48468.665 | G51: 2071100000
B52: 20712092001118 | C52: Travel expenses | D52: 1118 | E52: Gener Green LLC | F52: 23928.8 | G52: 2071209200
B53: 2071209200111111 | C53: Travel expenses | D53: 111111 | E53: External | F53: 2393259.2 | G53: 2071209200
B54: 2071209400111111 | C54: Utility expenses | D54: 111111 | E54: External | F54: 23069.655 | G54: 2071209400
B55: 2071209500111111 | C55: Legal expenses | D55: 111111 | E55: External | F55: 208366.93 | G55: 2071209500
B56: 2071220000111111 | C56: Losses fr disposal of PPE | D56: 111111 | E56: External | F56: 308232 | G56: 2071220000
B57: 207151100019 | C57: Other operative currency differences | D57: 19 | E57: Generco Cosmetics Ltd | F57: 13422.78 | G57: 2071511000
B58: 2071511000111111 | C58: Other operative currency differences | D58: 111111 | E58: External | F58: 4045.615 | G58: 2071511000
B59: 2071910000111111 | C59: Property tax | D59: 111111 | E59: External | F59: 49621.145 | G59: 2071910000
B60: 2071980000111101 | C60: Misc costs | D60: 111101 | E60: Not assigned | F60: 20323.31 | G60: 2071980000
B61: 2079022000111111 | C61: Consulting fees | D61: 111111 | E61: External | F61: 169489 | G61: 2079022000
B62: 207907000019 | C62: Misc extraordinary expenses | D62: 19 | E62: Generco Cosmetics Ltd | F62: 85462.685 | G62: 2079070000
B63: 207907000043 | C63: Misc extraordinary expenses | D63: 43 | E63: Greeny France SL | F63: 11422.145 | G63: 2079070000
B64: 20790700001924 | C64: Misc extraordinary expenses | D64: 1924 | E64: Generco Infrastructure Ltd | F64: 84438.865 | G64: 2079070000
B65: 2079070000111111 | C65: Misc extraordinary expenses | D65: 111111 | E65: External | F65: 638869.13 | G65: 2079070000
B66: 20790800001086 | C66: Difference from eliminations | D66: 1086 | E66: G&Resources Ltd | F66: 0 | G66: 2079080000
B67: 20790800001007 | C67: Difference from eliminations | D67: 1007 | E67: Generco Sunshine JSC | F67: 0 | G67: 2079080000
B68: 20790800001008 | C68: Difference from eliminations | D68: 1008 | E68: Greenco Ltd | F68: 0 | G68: 2079080000
B69: 20822800001086 | C69: Interest income | D69: 1086 | E69: G&Resources Ltd | F69: 0 | G69: 2082280000
B70: 20822800001009 | C70: Interest income | D70: 1009 | E70: Green Ventures Ltd | F70: 0 | G70: 2082280000
B71: 20822800001007 | C71: Interest income | D71: 1007 | E71: Generco Sunshine JSC | F71: 0 | G71: 2082280000
B72: 20822800001008 | C72: Interest income | D72: 1008 | E72: Greenco Ltd | F72: 0 | G72: 2082280000
B73: 20822800001240 | C73: Interest income | D73: 1240 | E73: Generco UK | F73: -34224.96 | G73: 2082280000
B74: 20822800001006 | C74: Interest income | D74: 1006 | E74: Generco Mining GmbH | F74: -6778.415 | G74: 2082280000
B75: 20822800001007 | C75: Interest income | D75: 1007 | E75: Generco Semiconductors Ltd | F75: 0 | G75: 2082280000
B76: 2082280000111111 | C76: Interest income | D76: 111111 | E76: External | F76: -2204.72 | G76: 2082280000
B77: 2082208200111101 | C77: Non-recurring costs | D77: 111101 | E77: Not assigned | F77: 80617.18 | G77: 2082208200
B78: 208221400088 | C78: Interest expenses | D78: 88 | E78: Generco Ltd | F78: 2752704.2 | G78: 2082214000
B79: 20822140001007 | C79: Interest expenses | D79: 1007 | E79: Generco Semiconductors Ltd | F79: 0 | G79: 2082214000
B80: 2082214000111111 | C80: Interest expenses | D80: 111111 | E80: External | F80: 1250.795 | G80: 2082214000
B81: 20821100001240 | C81: Impairment of participation | D81: 1240 | E81: Generco UK | F81: 4130000 | G81: 2082110000
... B86: 2111111999111101 | C86: Net income/(loss) | D86: 111101 | E86: Not assigned | F86: 6073808.2 | G86: 2111111999

Sheet 1.3 FY2026
B1: FY2026
B4: Code | C4: P&L account | D4: Partner company | E4: Name of partner company | F4: Amounts | G4: Account number
B5: 2001110000105 | C5: Core business revenues | D5: 105 | E5: Generco Healthcare Ltd | F5: -616462.02 | G5: 2001110000
B6: 2001110000111111 | C6: Core business revenues | D6: 111111 | E6: External | F6: -14431341 | G6: 2001110000
B7: 2001190000111111 | C7: Other revenues | D7: 111111 | E7: External | F7: -6373617.5 | G7: 2001190000
B8: 2021210000111111 | C8: Utility charges | D8: 111111 | E8: External | F8: 20504.51 | G8: 2021210000
B9: 2021900000111111 | C9: Direct costs | D9: 111111 | E9: External | F9: 5674152.1 | G9: 2021900000
B10: 2024020000111111 | C10: Operating expenses for utilities | D10: 111111 | E10: External | F10: 13691.95 | G10: 2024020000
B11: 2024080000111111 | C11: Freight outbound expenses | D11: 111111 | E11: External | F11: 350370.99 | G11: 2024080000
B12: 202409000088 | C12: R&D expenses | D12: 88 | E12: Generco Ltd | F12: 3116017.2 | G12: 2024090000
B13: 20240900001283 | C13: R&D expenses | D13: 1283 | E13: Generco Ventures Ltd | F13: 0 | G13: 2024090000
B14: 20240900001924 | C14: R&D expenses | D14: 1924 | E14: Generco Infrastructure Ltd | F14: 673.343 | G14: 2024090000
B15: 20240900002185 | C15: R&D expenses | D15: 2185 | E15: Generco Green Projects GmbH | F15: 192017.14 | G15: 2024090000
B16: 20240900002240 | C16: R&D expenses | D16: 2240 | E16: Greeny Germany GmbH | F16: 375290.47 | G16: 2024090000
B17: 202409000017000 | C17: R&D expenses | D17: 17000 | E17: Generco Risk Management Ltd | F17: 4920 | G17: 2024090000
B18: 2024090000111111 | C18: R&D expenses | D18: 111111 | E18: External | F18: 9783.707 | G18: 2024090000
B19: 2041000000111111 | C19: Wages and salaries | D19: 111111 | E19: External | F19: 3982699.5 | G19: 2041000000
B20: 2042000000111101 | C20: Social security payments | D20: 111101 | E20: Not assigned | F20: 1420796.8 | G20: 2042000000
B21: 2042000000111101 | C21: Pension contributions | D21: 111101 | E21: Not assigned | F21: 288891.82 | G21: 2042000000
B22: 2045000000111101 | C22: Severance indemnity contribution | D22: 111101 | E22: Not assigned | F22: 143500 | G22: 2045000000
B23: 2051210000111101 | C23: D&A | D23: 111101 | E23: Not assigned | F23: 1875768.2 | G23: 2051210000
B24: 2051260000111101 | C24: D&A | D24: 111101 | E24: Not assigned | F24: 12593.355 | G24: 2051260000
B25: 20604410001118 | C25: Other operative currency differences | D25: 1118 | E25: Gener Green LLC | F25: 0 | G25: 2060441000
B26: 2060441000111111 | C26: Other operative currency differences | D26: 111111 | E26: External | F26: -1252.837 | G26: 2060441000
B27: 20690100001 | C27: Corporate recharges | D27: 1 | E27: Greeny Ltd | F27: -1418521.4 | G27: 2069010000
B28: 206901000019 | C28: Corporate recharges | D28: 19 | E28: Generco Cosmetics Ltd | F28: -622966.39 | G28: 2069010000
B29: 20690100001076 | C29: Corporate recharges | D29: 1076 | E29: Generco Trading Ltd | F29: 0 | G29: 2069010000
B30: 20690100001086 | C30: Corporate recharges | D30: 1086 | E30: G&Resources Ltd | F30: 0 | G30: 2069010000
B31: 20690100001009 | C31: Corporate recharges | D31: 1009 | E31: Green Ventures Ltd | F31: 0 | G31: 2069010000
B32: 20690100001007 | C32: Corporate recharges | D32: 1007 | E32: Generco Sunshine JSC | F32: 0 | G32: 2069010000
B33: 20690100001008 | C33: Corporate recharges | D33: 1008 | E33: Greenco Ltd | F33: 0 | G33: 2069010000
B34: 20690100001240 | C34: Corporate recharges | D34: 1240 | E34: Generco UK | F34: 0 | G34: 2069010000
B35: 20690100001006 | C35: Corporate recharges | D35: 1006 | E35: Generco Mining GmbH | F35: 0 | G35: 2069010000
B36: 20690100001007 | C36: Corporate recharges | D36: 1007 | E36: Generco Semiconductors Ltd | F36: 0 | G36: 2069010000
B37: 206901000047037 | C37: Corporate recharges | D37: 47037 | E37: G&CR Global Ltd | F37: -1948832.1 | G37: 2069010000
B38: 2069010000111111 | C38: Corporate recharges | D38: 111111 | E38: External | F38: -902857.84 | G38: 2069010000
B39: 2069020000111111 | C39: Reimbursements+compensation for damages | D39: 111111 | E39: External | F39: -61500 | G39: 2069020000
B40: 2069980000105 | C40: Other income | D40: 105 | E40: Generco Healthcare Ltd | F40: -30913.426 | G40: 2069980000
B41: 2069980000111111 | C41: Other income | D41: 111111 | E41: External | F41: -15872.002 | G41: 2069980000
B42: 2070400000111111 | C42: Marketing expenses | D42: 111111 | E42: External | F42: 57.318 | G42: 2070400000
B43: 2070500000111111 | C43: Software&IT | D43: 111111 | E43: External | F43: 19198.66 | G43: 2070500000
B44: 2070600000105 | C44: Leasings | D44: 105 | E44: Generco Healthcare Ltd | F44: -1423120 | G44: 2070600000
B45: 2070600000111111 | C45: Leasings | D45: 111111 | E45: External | F45: -172933.45 | G45: 2070600000
B46: 2070900000105 | C46: Service expenses | D46: 105 | E46: Generco Healthcare Ltd | F46: 473575.46 | G46: 2070900000
B47: 2070900000111111 | C47: Service expenses | D47: 111111 | E47: External | F47: 1481408.5 | G47: 2070900000
B48: 2071000000111111 | C48: Charges and contributions | D48: 111111 | E48: External | F48: 40048.8 | G48: 2071000000
B49: 207110000088 | C49: Insurance expenses | D49: 88 | E49: Generco Ltd | F49: 584.66 | G49: 2071100000
... B56: 2079022000111111 | C56: Consulting fees | D56: 111111 | E56: External | F56: 61111.484 | G56: 2079022000
B57: 20790700001924 | C57: Misc extraordinary expenses | D57: 1924 | E57: Generco Infrastructure Ltd | F57: 0 | G57: 2079070000
B58: 2079070000105 | C58: Misc extraordinary expenses | D58: 105 | E58: Generco Healthcare Ltd | F58: 1684415.3 | G58: 2079070000
B59: 2079070000111111 | C59: Misc extraordinary expenses | D59: 111111 | E59: External | F59: 575626.26 | G59: 2079070000
B60: 20790800001086 | C60: Difference from eliminations | D60: 1086 | E60: G&Resources Ltd | F60: 0 | G60: 2079080000
B61: 20790800001007 | C61: Difference from eliminations | D61: 1007 | E61: Generco Semiconductors Ltd | F61: 0 | G61: 2079080000
B62: 20822800001086 | C62: Interest income | D62: 1086 | E62: G&Resources Ltd | F62: 0 | G62: 2082280000
B63: 20822800001009 | C63: Interest income | D63: 1009 | E63: Green Ventures Ltd | F63: 0 | G63: 2082280000
B64: 20822800001007 | C64: Interest income | D64: 1007 | E64: Generco Sunshine JSC | F64: 0 | G64: 2082280000
B65: 20822800001008 | C65: Interest income | D65: 1008 | E65: Greenco Ltd | F65: 0 | G65: 2082280000
B66: 20822800001240 | C66: Interest income | D66: 1240 | E66: Generco UK | F66: 0 | G66: 2082280000
B67: 20822800001006 | C67: Interest income | D67: 1006 | E67: Generco Mining GmbH | F67: 0 | G67: 2082280000
B68: 2082280000111111 | C68: Interest income | D68: 111111 | E68: External | F68: -73809.512 | G68: 2082280000
B69: 2082208200111101 | C69: Non-recurring costs | D69: 111101 | E69: Not assigned | F69: 7173.196 | G69: 2082208200
B70: 208221400088 | C70: Interest expenses | D70: 88 | E70: Generco Ltd | F70: 2324465.9 | G70: 2082214000
B71: 20822140001007 | C71: Interest expenses | D71: 1007 | E71: Generco Semiconductors Ltd | F71: 0 | G71: 2082214000
B72: 2082214000111111 | C72: Interest expenses | D72: 111111 | E72: External | F72: 51.455 | G72: 2082214000
B73: 2082110000111101 | C73: Impairment of participation | D73: 111101 | E73: Not assigned | F73: 0 | G73: 2082110000
B74: 2091200000111101 | C74: Current taxes | D74: 111101 | E74: Not assigned | F74: 2558.195 | G74: 2091200000
... B78: 2111111999111101 | C78: Net income/(loss) | D78: 111101 | E78: Not assigned | F78: -779290.48 | G78: 2111111999

Sheet Database
B1: Creating a "Database"
B3: Code | C3: P&L account | D3: Partner company | E3: Name of partner company | F3: FY24 | G3: FY25 | H3: FY26 | I3: Mapping | J3: Checking the Mapping
B4: 2001110000111111 | C4: =VLOOKUP(B4,'1.1 FY2024'!$B$4:$G$61,2,FALSE) -> Core business revenues | D4: =VLOOKUP(B4,'1.1 FY2024'!$B$4:$G$61,3,FALSE) -> 111111 | E4: =VLOOKUP(B4,'1.1 FY2024'!$B$4:$G$61,4,FALSE) -> External | F4: =-SUMIF('1.1 FY2024'!$B:$B,Database!B4,'1.1 FY2024'!$F:$F) -> 14500341 | G4: =-SUMIF('1.2 FY2025'!$B:$B,Database!B4,'1.2 FY2025'!$F:$F) -> 15792899 | H4: =-SUMIF('1.3 FY2026'!$B:$B,Database!B4,'1.3 FY2026'!$F:$F) -> 14431341 | I4: Net Sales | J4: =COUNTIF('P&L Model'!$B$4:$B$24,Database!I4) -> 1
B5: 2001190000111111 | C5: =VLOOKUP(B5,'1.1 FY2024'!$B$4:$G$61,2,FALSE) -> Other revenues | D5: =VLOOKUP(B5,'1.1 FY2024'!$B$4:$G$61,3,FALSE) -> 111111 | E5: =VLOOKUP(B5,'1.1 FY2024'!$B$4:$G$61,4,FALSE) -> External | F5: =-SUMIF('1.1 FY2024'!$B:$B,Database!B5,'1.1 FY2024'!$F:$F) -> 4794856.2 | G5: =-SUMIF('1.2 FY2025'!$B:$B,Database!B5,'1.2 FY2025'!$F:$F) -> 6960217.6 | H5: =-SUMIF('1.3 FY2026'!$B:$B,Database!B5,'1.3 FY2026'!$F:$F) -> 6373617.5 | I5: Other revenues | J5: =COUNTIF('P&L Model'!$B$4:$B$24,Database!I5) -> 1
B6: 20200000001009 | C6: =VLOOKUP(B6,'1.1 FY2024'!$B$4:$G$61,2,FALSE) -> Capitalized costs | D6: =VLOOKUP(B6,'1.1 FY2024'!$B$4:$G$61,3,FALSE) -> 1009 | E6: =VLOOKUP(B6,'1.1 FY2024'!$B$4:$G$61,4,FALSE) -> Green Ventures Ltd | F6: =-SUMIF('1.1 FY2024'!$B:$B,Database!B6,'1.1 FY2024'!$F:$F) -> 154890.4 | G6: =-SUMIF('1.2 FY2025'!$B:$B,Database!B6,'1.2 FY2025'!$F:$F) -> 0 | H6: =-SUMIF('1.3 FY2026'!$B:$B,Database!B6,'1.3 FY2026'!$F:$F) -> 0 | I6: Capitalized costs | J6: =COUNTIF('P&L Model'!$B$4:$B$24,Database!I6) -> 1
B7: 20200000001007 | C7: =VLOOKUP(B7,'1.1 FY2024'!$B$4:$G$61,2,FALSE) -> Capitalized costs | D7: =VLOOKUP(B7,'1.1 FY2024'!$B$4:$G$61,3,FALSE) -> 1007 | E7: =VLOOKUP(B7,'1.1 FY2024'!$B$4:$G$61,4,FALSE) -> Generco Sunshine JSC | F7: =-SUMIF('1.1 FY2024'!$B:$B,Database!B7,'1.1 FY2024'!$F:$F) -> 1180894.1 | G7: =-SUMIF('1.2 FY2025'!$B:$B,Database!B7,'1.2 FY2025'!$F:$F) -> 89234.88 | H7: =-SUMIF('1.3 FY2026'!$B:$B,Database!B7,'1.3 FY2026'!$F:$F) -> 0 | I7: Capitalized costs | J7: =COUNTIF('P&L Model'!$B$4:$B$24,Database!I7) -> 1
B8: 20200000001008 | C8: =VLOOKUP(B8,'1.1 FY2024'!$B$4:$G$61,2,FALSE) -> Capitalized costs | D8: =VLOOKUP(B8,'1.1 FY2024'!$B$4:$G$61,3,FALSE) -> 1008 | E8: =VLOOKUP(B8,'1.1 FY2024'!$B$4:$G$61,4,FALSE) -> Greenco Ltd | F8: =-SUMIF('1.1 FY2024'!$B:$B,Database!B8,'1.1 FY2024'!$F:$F) -> 793079.51 | G8: =-SUMIF('1.2 FY2025'!$B:$B,Database!B8,'1.2 FY2025'!$F:$F) -> 26173 | H8: =-SUMIF('1.3 FY2026'!$B:$B,Database!B8,'1.3 FY2026'!$F:$F) -> 0 | I8: Capitalized costs | J8: =COUNTIF('P&L Model'!$B$4:$B$24,Database!I8) -> 1
B9: 2020000000111101 | C9: =VLOOKUP(B9,'1.1 FY2024'!$B$4:$G$61,2,FALSE) -> Capitalized costs | D9: =VLOOKUP(B9,'1.1 FY2024'!$B$4:$G$61,3,FALSE) -> 111101 | E9: =VLOOKUP(B9,'1.1 FY2024'!$B$4:$G$61,4,FALSE) -> Not assigned | F9: =-SUMIF('1.1 FY2024'!$B:$B,Database!B9,'1.1 FY2024'!$F:$F) -> 2277197.6 | G9: =-SUMIF('1.2 FY2025'!$B:$B,Database!B9,'1.2 FY2025'!$F:$F) -> 209401.92 | H9: =-SUMIF('1.3 FY2026'!$B:$B,Database!B9,'1.3 FY2026'!$F:$F) -> 0 | I9: Capitalized costs | J9: =COUNTIF('P&L Model'!$B$4:$B$24,Database!I9) -> 1
B10: 2021900000111111 | C10: =VLOOKUP(B10,'1.1 FY2024'!$B$4:$G$61,2,FALSE) -> Direct costs | D10: =VLOOKUP(B10,'1.1 FY2024'!$B$4:$G$61,3,FALSE) -> 111111 | E10: =VLOOKUP(B10,'1.1 FY2024'!$B$4:$G$61,4,FALSE) -> External | F10: =-SUMIF('1.1 FY2024'!$B:$B,Database!B10,'1.1 FY2024'!$F:$F) -> -4428911.8 | G10: =-SUMIF('1.2 FY2025'!$B:$B,Database!B10,'1.2 FY2025'!$F:$F) -> -5463188.8 | H10: =-SUMIF('1.3 FY2026'!$B:$B,Database!B10,'1.3 FY2026'!$F:$F) -> -5674152.1 | I10: Direct costs | J10: =COUNTIF('P&L Model'!$B$4:$B$24,Database!I10) -> 1
B11: 2024080000111111 | C11: =VLOOKUP(B11,'1.1 FY2024'!$B$4:$G$61,2,FALSE) -> Freight outbound expenses | D11: =VLOOKUP(B11,'1.1 FY2024'!$B$4:$G$61,3,FALSE) -> 111111 | E11: =VLOOKUP(B11,'1.1 FY2024'!$B$4:$G$61,4,FALSE) -> External | F11: =-SUMIF('1.1 FY2024'!$B:$B,Database!B11,'1.1 FY2024'!$F:$F) -> -16977.628 | G11: =-SUMIF('1.2 FY2025'!$B:$B,Database!B11,'1.2 FY2025'!$F:$F) -> -343675 | H11: =-SUMIF('1.3 FY2026'!$B:$B,Database!B11,'1.3 FY2026'!$F:$F) -> -350370.99 | I11: Other operating expenses | J11: =COUNTIF('P&L Model'!$B$4:$B$24,Database!I11) -> 1
B12: 202409000088 | C12: =VLOOKUP(B12,'1.1 FY2024'!$B$4:$G$61,2,FALSE) -> R&D expenses | D12: =VLOOKUP(B12,'1.1 FY2024'!$B$4:$G$61,3,FALSE) -> 88 | E12: =VLOOKUP(B12,'1.1 FY2024'!$B$4:$G$61,4,FALSE) -> Generco Ltd | F12: =-SUMIF('1.1 FY2024'!$B:$B,Database!B12,'1.1 FY2024'!$F:$F) -> -2245437.5 | G12: =-SUMIF('1.2 FY2025'!$B:$B,Database!B12,'1.2 FY2025'!$F:$F) -> -1980162.2 | H12: =-SUMIF('1.3 FY2026'!$B:$B,Database!B12,'1.3 FY2026'!$F:$F) -> -3116017.2 | I12: Other operating expenses | J12: =COUNTIF('P&L Model'!$B$4:$B$24,Database!I12) -> 1
B13: 2024090000111111 | C13: =VLOOKUP(B13,'1.1 FY2024'!$B$4:$G$61,2,FALSE) -> R&D expenses | D13: =VLOOKUP(B13,'1.1 FY2024'!$B$4:$G$61,3,FALSE) -> 111111 | E13: =VLOOKUP(B13,'1.1 FY2024'!$B$4:$G$61,4,FALSE) -> External | F13: =-SUMIF('1.1 FY2024'!$B:$B,Database!B13,'1.1 FY2024'!$F:$F) -> -16605.634 | G13: =-SUMIF('1.2 FY2025'!$B:$B,Database!B13,'1.2 FY2025'!$F:$F) -> -27148.625 | H13: =-SUMIF('1.3 FY2026'!$B:$B,Database!B13,'1.3 FY2026'!$F:$F) -> -9783.707 | I13: Other operating expenses | J13: =COUNTIF('P&L Model'!$B$4:$B$24,Database!I13) -> 1
B14: 2041000000111111 | C14: =VLOOKUP(B14,'1.1 FY2024'!$B$4:$G$61,2,FALSE) -> Wages and salaries | D14: =VLOOKUP(B14,'1.1 FY2024'!$B$4:$G$61,3,FALSE) -> 111111 | E14: =VLOOKUP(B14,'1.1 FY2024'!$B$4:$G$61,4,FALSE) -> External | F14: =-SUMIF('1.1 FY2024'!$B:$B,Database!B14,'1.1 FY2024'!$F:$F) -> -4683394 | G14: =-SUMIF('1.2 FY2025'!$B:$B,Database!B14,'1.2 FY2025'!$F:$F) -> -5507141.1 | H14: =-SUMIF('1.3 FY2026'!$B:$B,Database!B14,'1.3 FY2026'!$F:$F) -> -3982699.5 | I14: Personnel expenses | J14: =COUNTIF('P&L Model'!$B$4:$B$24,Database!I14) -> 1
B15: 2042000000111101 | C15: =VLOOKUP(B15,'1.1 FY2024'!$B$4:$G$61,2,FALSE) -> Pension contributions | D15: =VLOOKUP(B15,'1.1 FY2024'!$B$4:$G$61,3,FALSE) -> 111101 | E15: =VLOOKUP(B15,'1.1 FY2024'!$B$4:$G$61,4,FALSE) -> Not assigned | F15: =-SUMIF('1.1 FY2024'!$B:$B,Database!B15,'1.1 FY2024'!$F:$F) -> -1143051.6 | G15: =-SUMIF('1.2 FY2025'!$B:$B,Database!B15,'1.2 FY2025'!$F:$F) -> -2057298 | H15: =-SUMIF('1.3 FY2026'!$B:$B,Database!B15,'1.3 FY2026'!$F:$F) -> -1709688.6 | I15: Personnel expenses | J15: =COUNTIF('P&L Model'!$B$4:$B$24,Database!I15) -> 1
... B45: 2079070000111111 | C45: =VLOOKUP(B45,'1.1 FY2024'!$B$4:$G$61,2,FALSE) -> Misc extraordinary expenses | D45: =VLOOKUP(B45,'1.1 FY2024'!$B$4:$G$61,3,FALSE) -> 111111 | E45: =VLOOKUP(B45,'1.1 FY2024'!$B$4:$G$61,4,FALSE) -> External | F45: =-SUMIF('1.1 FY2024'!$B:$B,Database!B45,'1.1 FY2024'!$F:$F) -> -563918.15 | G45: =-SUMIF('1.2 FY2025'!$B:$B,Database!B45,'1.2 FY2025'!$F:$F) -> -638869.13 | H45: =-SUMIF('1.3 FY2026'!$B:$B,Database!B45,'1.3 FY2026'!$F:$F) -> -575626.26 | I45: Other operating expenses | J45: =COUNTIF('P&L Model'!$B$4:$B$24,Database!I45) -> 1
B46: 20790800001009 | C46: =VLOOKUP(B46,'1.1 FY2024'!$B$4:$G$61,2,FALSE) -> Difference from eliminations | D46: =VLOOKUP(B46,'1.1 FY2024'!$B$4:$G$61,3,FALSE) -> 1009 | E46: =VLOOKUP(B46,'1.1 FY2024'!$B$4:$G$61,4,FALSE) -> Green Ventures Ltd | F46: =-SUMIF('1.1 FY2024'!$B:$B,Database!B46,'1.1 FY2024'!$F:$F) -> 0 | G46: =-SUMIF('1.2 FY2025'!$B:$B,Database!B46,'1.2 FY2025'!$F:$F) -> 0 | H46: =-SUMIF('1.3 FY2026'!$B:$B,Database!B46,'1.3 FY2026'!$F:$F) -> 0 | J46: =COUNTIF('P&L Model'!$B$4:$B$24,Database!I46) -> 0
B47: 20790800001007 | C47: =VLOOKUP(B47,'1.1 FY2024'!$B$4:$G$61,2,FALSE) -> Difference from eliminations | D47: =VLOOKUP(B47,'1.1 FY2024'!$B$4:$G$61,3,FALSE) -> 1007 | E47: =VLOOKUP(B47,'1.1 FY2024'!$B$4:$G$61,4,FALSE) -> Generco Sunshine JSC | F47: =-SUMIF('1.1 FY2024'!$B:$B,Database!B47,'1.1 FY2024'!$F:$F) -> 0 | G47: =-SUMIF('1.2 FY2025'!$B:$B,Database!B47,'1.2 FY2025'!$F:$F) -> 0 | H47: =-SUMIF('1.3 FY2026'!$B:$B,Database!B47,'1.3 FY2026'!$F:$F) -> 0 | J47: =COUNTIF('P&L Model'!$B$4:$B$24,Database!I47) -> 0
B48: 20790800001008 | C48: =VLOOKUP(B48,'1.1 FY2024'!$B$4:$G$61,2,FALSE) -> Difference from eliminations | D48: =VLOOKUP(B48,'1.1 FY2024'!$B$4:$G$61,3,FALSE) -> 1008 | E48: =VLOOKUP(B48,'1.1 FY2024'!$B$4:$G$61,4,FALSE) -> Greenco Ltd | F48: =-SUMIF('1.1 FY2024'!$B:$B,Database!B48,'1.1 FY2024'!$F:$F) -> 0 | G48: =-SUMIF('1.2 FY2025'!$B:$B,Database!B48,'1.2 FY2025'!$F:$F) -> 0 | H48: =-SUMIF('1.3 FY2026'!$B:$B,Database!B48,'1.3 FY2026'!$F:$F) -> 0 | J48: =COUNTIF('P&L Model'!$B$4:$B$24,Database!I48) -> 0
B49: 20822800001009 | C49: =VLOOKUP(B49,'1.1 FY2024'!$B$4:$G$61,2,FALSE) -> Interest income | D49: =VLOOKUP(B49,'1.1 FY2024'!$B$4:$G$61,3,FALSE) -> 1009 | E49: =VLOOKUP(B49,'1.1 FY2024'!$B$4:$G$61,4,FALSE) -> Green Ventures Ltd | F49: =-SUMIF('1.1 FY2024'!$B:$B,Database!B49,'1.1 FY2024'!$F:$F) -> 0 | G49: =-SUMIF('1.2 FY2025'!$B:$B,Database!B49,'1.2 FY2025'!$F:$F) -> 0 | H49: =-SUMIF('1.3 FY2026'!$B:$B,Database!B49,'1.3 FY2026'!$F:$F) -> 0 | I49: Financial items | J49: =COUNTIF('P&L Model'!$B$4:$B$24,Database!I49) -> 1
B50: 20822800001007 | C50: =VLOOKUP(B50,'1.1 FY2024'!$B$4:$G$61,2,FALSE) -> Interest income | D50: =VLOOKUP(B50,'1.1 FY2024'!$B$4:$G$61,3,FALSE) -> 1007 | E50: =VLOOKUP(B50,'1.1 FY2024'!$B$4:$G$61,4,FALSE) -> Generco Sunshine JSC | F50: =-SUMIF('1.1 FY2024'!$B:$B,Database!B50,'1.1 FY2024'!$F:$F) -> 0 | G50: =-SUMIF('1.2 FY2025'!$B:$B,Database!B50,'1.2 FY2025'!$F:$F) -> 0 | H50: =-SUMIF('1.3 FY2026'!$B:$B,Database!B50,'1.3 FY2026'!$F:$F) -> 0 | I50: Financial items | J50: =COUNTIF('P&L Model'!$B$4:$B$24,Database!I50) -> 1
B51: 20822800001008 | C51: =VLOOKUP(B51,'1.1 FY2024'!$B$4:$G$61,2,FALSE) -> Interest income | D51: =VLOOKUP(B51,'1.1 FY2024'!$B$4:$G$61,3,FALSE) -> 1008 | E51: =VLOOKUP(B51,'1.1 FY2024'!$B$4:$G$61,4,FALSE) -> Greenco Ltd | F51: =-SUMIF('1.1 FY2024'!$B:$B,Database!B51,'1.1 FY2024'!$F:$F) -> 0 | G51: =-SUMIF('1.2 FY2025'!$B:$B,Database!B51,'1.2 FY2025'!$F:$F) -> 0 | H51: =-SUMIF('1.3 FY2026'!$B:$B,Database!B51,'1.3 FY2026'!$F:$F) -> 0 | I51: Financial items | J51: =COUNTIF('P&L Model'!$B$4:$B$24,Database!I51) -> 1
B52: 20822800001240 | C52: =VLOOKUP(B52,'1.1 FY2024'!$B$4:$G$61,2,FALSE) -> Interest income | D52: =VLOOKUP(B52,'1.1 FY2024'!$B$4:$G$61,3,FALSE) -> 1240 | E52: =VLOOKUP(B52,'1.1 FY2024'!$B$4:$G$61,4,FALSE) -> Generco UK | F52: =-SUMIF('1.1 FY2024'!$B:$B,Database!B52,'1.1 FY2024'!$F:$F) -> 35810.228 | G52: =-SUMIF('1.2 FY2025'!$B:$B,Database!B52,'1.2 FY2025'!$F:$F) -> 34224.96 | H52: =-SUMIF('1.3 FY2026'!$B:$B,Database!B52,'1.3 FY2026'!$F:$F) -> 0 | I52: Financial items | J52: =COUNTIF('P&L Model'!$B$4:$B$24,Database!I52) -> 1
B53: 2082280000111111 | C53: =VLOOKUP(B53,'1.1 FY2024'!$B$4:$G$61,2,FALSE) -> Interest income | D53: =VLOOKUP(B53,'1.1 FY2024'!$B$4:$G$61,3,FALSE) -> 111111 | E53: =VLOOKUP(B53,'1.1 FY2024'!$B$4:$G$61,4,FALSE) -> External | F53: =-SUMIF('1.1 FY2024'!$B:$B,Database!B53,'1.1 FY2024'!$F:$F) -> 51927.418 | G53: =-SUMIF('1.2 FY2025'!$B:$B,Database!B53,'1.2 FY2025'!$F:$F) -> 2204.72 | H53: =-SUMIF('1.3 FY2026'!$B:$B,Database!B53,'1.3 FY2026'!$F:$F) -> 73809.512 | I53: Financial items | J53: =COUNTIF('P&L Model'!$B$4:$B$24,Database!I53) -> 1
B54: 2082202000111101 | C54: =VLOOKUP(B54,'1.1 FY2024'!$B$4:$G$61,2,FALSE) -> Capitalized interest | D54: =VLOOKUP(B54,'1.1 FY2024'!$B$4:$G$61,3,FALSE) -> 111101 | E54: =VLOOKUP(B54,'1.1 FY2024'!$B$4:$G$61,4,FALSE) -> Not assigned | F54: =-SUMIF('1.1 FY2024'!$B:$B,Database!B54,'1.1 FY2024'!$F:$F) -> 862270.63 | G54: =-SUMIF('1.2 FY2025'!$B:$B,Database!B54,'1.2 FY2025'!$F:$F) -> 0 | H54: =-SUMIF('1.3 FY2026'!$B:$B,Database!B54,'1.3 FY2026'!$F:$F) -> 0 | I54: Capitalized costs | J54: =COUNTIF('P&L Model'!$B$4:$B$24,Database!I54) -> 1
B55: 2082208200111101 | C55: =VLOOKUP(B55,'1.1 FY2024'!$B$4:$G$61,2,FALSE) -> Non-recurring costs | D55: =VLOOKUP(B55,'1.1 FY2024'!$B$4:$G$61,3,FALSE) -> 111101 | E55: =VLOOKUP(B55,'1.1 FY2024'!$B$4:$G$61,4,FALSE) -> Not assigned | F55: =-SUMIF('1.1 FY2024'!$B:$B,Database!B55,'1.1 FY2024'!$F:$F) -> -22763 | G55: =-SUMIF('1.2 FY2025'!$B:$B,Database!B55,'1.2 FY2025'!$F:$F) -> -80617.18 | H55: =-SUMIF('1.3 FY2026'!$B:$B,Database!B55,'1.3 FY2026'!$F:$F) -> -7173.196 | I55: Extraordinary items | J55: =COUNTIF('P&L Model'!$B$4:$B$24,Database!I55) -> 1
B56: 208221400088 | C56: =VLOOKUP(B56,'1.1 FY2024'!$B$4:$G$61,2,FALSE) -> Interest expenses | D56: =VLOOKUP(B56,'1.1 FY2024'!$B$4:$G$61,3,FALSE) -> 88 | E56: =VLOOKUP(B56,'1.1 FY2024'!$B$4:$G$61,4,FALSE) -> Generco Ltd | F56: =-SUMIF('1.1 FY2024'!$B:$B,Database!B56,'1.1 FY2024'!$F:$F) -> -2930430 | G56: =-SUMIF('1.2 FY2025'!$B:$B,Database!B56,'1.2 FY2025'!$F:$F) -> -2752704.2 | H56: =-SUMIF('1.3 FY2026'!$B:$B,Database!B56,'1.3 FY2026'!$F:$F) -> -2324465.9 | I56: Financial items | J56: =COUNTIF('P&L Model'!$B$4:$B$24,Database!I56) -> 1
B57: 2091200000111101 | C57: =VLOOKUP(B57,'1.1 FY2024'!$B$4:$G$61,2,FALSE) -> Current taxes | D57: =VLOOKUP(B57,'1.1 FY2024'!$B$4:$G$61,3,FALSE) -> 111101 | E57: =VLOOKUP(B57,'1.1 FY2024'!$B$4:$G$61,4,FALSE) -> Not assigned | F57: =-SUMIF('1.1 FY2024'!$B:$B,Database!B57,'1.1 FY2024'!$F:$F) -> 49378.642 | G57: =-SUMIF('1.2 FY2025'!$B:$B,Database!B57,'1.2 FY2025'!$F:$F) -> -496748.7 | H57: =-SUMIF('1.3 FY2026'!$B:$B,Database!B57,'1.3 FY2026'!$F:$F) -> -2558.195 | I57: Taxes | J57: =COUNTIF('P&L Model'!$B$4:$B$24,Database!I57) -> 1
B58: 2091200001111101 | C58: =VLOOKUP(B58,'1.1 FY2024'!$B$4:$G$61,2,FALSE) -> Regional taxes | D58: =VLOOKUP(B58,'1.1 FY2024'!$B$4:$G$61,3,FALSE) -> 111101 | E58: =VLOOKUP(B58,'1.1 FY2024'!$B$4:$G$61,4,FALSE) -> Not assigned | F58: =-SUMIF('1.1 FY2024'!$B:$B,Database!B58,'1.1 FY2024'!$F:$F) -> -516250.67 | G58: =-SUMIF('1.2 FY2025'!$B:$B,Database!B58,'1.2 FY2025'!$F:$F) -> -480872.96 | H58: =-SUMIF('1.3 FY2026'!$B:$B,Database!B58,'1.3 FY2026'!$F:$F) -> -522710.35 | I58: Taxes | J58: =COUNTIF('P&L Model'!$B$4:$B$24,Database!I58) -> 1
B59: 2092200000111101 | C59: =VLOOKUP(B59,'1.1 FY2024'!$B$4:$G$61,2,FALSE) -> Deferred taxes | D59: =VLOOKUP(B59,'1.1 FY2024'!$B$4:$G$61,3,FALSE) -> 111101 | E59: =VLOOKUP(B59,'1.1 FY2024'!$B$4:$G$61,4,FALSE) -> Not assigned | F59: =-SUMIF('1.1 FY2024'!$B:$B,Database!B59,'1.1 FY2024'!$F:$F) -> -21593.094 | G59: =-SUMIF('1.2 FY2025'!$B:$B,Database!B59,'1.2 FY2025'!$F:$F) -> -6570.305 | H59: =-SUMIF('1.3 FY2026'!$B:$B,Database!B59,'1.3 FY2026'!$F:$F) -> 160303.52 | I59: Taxes | J59: =COUNTIF('P&L Model'!$B$4:$B$24,Database!I59) -> 1
B60: 2999999999111101 | C60: =VLOOKUP(B60,'1.1 FY2024'!$B$4:$G$61,2,FALSE) -> Net income/(loss) | D60: =VLOOKUP(B60,'1.1 FY2024'!$B$4:$G$61,3,FALSE) -> 111101 | E60: =VLOOKUP(B60,'1.1 FY2024'!$B$4:$G$61,4,FALSE) -> Not assigned | F60: =-SUMIF('1.1 FY2024'!$B:$B,Database!B60,'1.1 FY2024'!$F:$F) -> 2904118 | G60: =-SUMIF('1.2 FY2025'!$B:$B,Database!B60,'1.2 FY2025'!$F:$F) -> 0 | H60: =-SUMIF('1.3 FY2026'!$B:$B,Database!B60,'1.3 FY2026'!$F:$F) -> 0 | I60: Net Income | J60: =COUNTIF('P&L Model'!$B$4:$B$24,Database!I60) -> 1
B61: 2001110000105 | C61: - | D61: - | E61: - | F61: =-SUMIF('1.1 FY2024'!$B:$B,Database!B61,'1.1 FY2024'!$F:$F) -> 0 | G61: =-SUMIF('1.2 FY2025'!$B:$B,Database!B61,'1.2 FY2025'!$F:$F) -> 355396.61 | H61: =-SUMIF('1.3 FY2026'!$B:$B,Database!B61,'1.3 FY2026'!$F:$F) -> 616462.02 | I61: Net sales | J61: =COUNTIF('P&L Model'!$B$4:$B$24,Database!I61) -> 1
B62: 20200000001086 | C62: - | D62: - | E62: - | F62: =-SUMIF('1.1 FY2024'!$B:$B,Database!B62,'1.1 FY2024'!$F:$F) -> 0 | G62: =-SUMIF('1.2 FY2025'!$B:$B,Database!B62,'1.2 FY2025'!$F:$F) -> 420017.15 | H62: =-SUMIF('1.3 FY2026'!$B:$B,Database!B62,'1.3 FY2026'!$F:$F) -> 0 | I62: Capitalized costs | J62: =COUNTIF('P&L Model'!$B$4:$B$24,Database!I62) -> 1
B63: 2021210000111111 | C63: - | D63: - | E63: - | F63: =-SUMIF('1.1 FY2024'!$B:$B,Database!B63,'1.1 FY2024'!$F:$F) -> 0 | G63: =-SUMIF('1.2 FY2025'!$B:$B,Database!B63,'1.2 FY2025'!$F:$F) -> -14589.33 | H63: =-SUMIF('1.3 FY2026'!$B:$B,Database!B63,'1.3 FY2026'!$F:$F) -> -20504.51 | I63: Other operating expenses | J63: =COUNTIF('P&L Model'!$B$4:$B$24,Database!I63) -> 1
B64: 202409000019 | C64: - | D64: - | E64: - | F64: =-SUMIF('1.1 FY2024'!$B:$B,Database!B64,'1.1 FY2024'!$F:$F) -> 0 | G64: =-SUMIF('1.2 FY2025'!$B:$B,Database!B64,'1.2 FY2025'!$F:$F) -> -38521 | H64: =-SUMIF('1.3 FY2026'!$B:$B,Database!B64,'1.3 FY2026'!$F:$F) -> 0 | I64: Other operating expenses | J64: =COUNTIF('P&L Model'!$B$4:$B$24,Database!I64) -> 1
B65: 20240900001283 | C65: - | D65: - | E65: - | F65: =-SUMIF('1.1 FY2024'!$B:$B,Database!B65,'1.1 FY2024'!$F:$F) -> 0 | G65: =-SUMIF('1.2 FY2025'!$B:$B,Database!B65,'1.2 FY2025'!$F:$F) -> -1820 | H65: =-SUMIF('1.3 FY2026'!$B:$B,Database!B65,'1.3 FY2026'!$F:$F) -> 0 | I65: Other operating expenses | J65: =COUNTIF('P&L Model'!$B$4:$B$24,Database!I65) -> 1
B66: 20240900001924 | C66: - | D66: - | E66: - | F66: =-SUMIF('1.1 FY2024'!$B:$B,Database!B66,'1.1 FY2024'!$F:$F) -> 0 | G66: =-SUMIF('1.2 FY2025'!$B:$B,Database!B66,'1.2 FY2025'!$F:$F) -> -10448.13 | H66: =-SUMIF('1.3 FY2026'!$B:$B,Database!B66,'1.3 FY2026'!$F:$F) -> -673.343 | I66: Other operating expenses | J66: =COUNTIF('P&L Model'!$B$4:$B$24,Database!I66) -> 1
B67: 20240900002486 | C67: - | D67: - | E67: - | F67: =-SUMIF('1.1 FY2024'!$B:$B,Database!B67,'1.1 FY2024'!$F:$F) -> 0 | G67: =-SUMIF('1.2 FY2025'!$B:$B,Database!B67,'1.2 FY2025'!$F:$F) -> -10412.5 | H67: =-SUMIF('1.3 FY2026'!$B:$B,Database!B67,'1.3 FY2026'!$F:$F) -> 0 | I67: Other operating expenses | J67: =COUNTIF('P&L Model'!$B$4:$B$24,Database!I67) -> 1
B68: 2049000000111101 | C68: - | D68: - | E68: - | F68: =-SUMIF('1.1 FY2024'!$B:$B,Database!B68,'1.1 FY2024'!$F:$F) -> 0 | G68: =-SUMIF('1.2 FY2025'!$B:$B,Database!B68,'1.2 FY2025'!$F:$F) -> -6919.85 | H68: =-SUMIF('1.3 FY2026'!$B:$B,Database!B68,'1.3 FY2026'!$F:$F) -> 0 | I68: Personnel expenses | J68: =COUNTIF('P&L Model'!$B$4:$B$24,Database!I68) -> 1
B69: 2051260000111101 | C69: - | D69: - | E69: - | F69: =-SUMIF('1.1 FY2024'!$B:$B,Database!B69,'1.1 FY2024'!$F:$F) -> 0 | G69: =-SUMIF('1.2 FY2025'!$B:$B,Database!B69,'1.2 FY2025'!$F:$F) -> -146328.94 | H69: =-SUMIF('1.3 FY2026'!$B:$B,Database!B69,'1.3 FY2026'!$F:$F) -> -12593.355 | I69: D&A | J69: =COUNTIF('P&L Model'!$B$4:$B$24,Database!I69) -> 1
B70: 2060220000111111 | C70: - | D70: - | E70: - | F70: =-SUMIF('1.1 FY2024'!$B:$B,Database!B70,'1.1 FY2024'!$F:$F) -> 0 | G70: =-SUMIF('1.2 FY2025'!$B:$B,Database!B70,'1.2 FY2025'!$F:$F) -> 121553.07 | H70: =-SUMIF('1.3 FY2026'!$B:$B,Database!B70,'1.3 FY2026'!$F:$F) -> 0 | I70: Extraordinary items | J70: =COUNTIF('P&L Model'!$B$4:$B$24,Database!I70) -> 1
B71: 206901000019 | C71: - | D71: - | E71: - | F71: =-SUMIF('1.1 FY2024'!$B:$B,Database!B71,'1.1 FY2024'!$F:$F) -> 0 | G71: =-SUMIF('1.2 FY2025'!$B:$B,Database!B71,'1.2 FY2025'!$F:$F) -> 416278.66 | H71: =-SUMIF('1.3 FY2026'!$B:$B,Database!B71,'1.3 FY2026'!$F:$F) -> 622966.39 | I71: Recharges | J71: =COUNTIF('P&L Model'!$B$4:$B$24,Database!I71) -> 1
B72: 20690100001076 | C72: - | D72: - | E72: - | F72: =-SUMIF('1.1 FY2024'!$B:$B,Database!B72,'1.1 FY2024'!$F:$F) -> 0 | G72: =-SUMIF('1.2 FY2025'!$B:$B,Database!B72,'1.2 FY2025'!$F:$F) -> 364243.84 | H72: =-SUMIF('1.3 FY2026'!$B:$B,Database!B72,'1.3 FY2026'!$F:$F) -> 0 | I72: Recharges | J72: =COUNTIF('P&L Model'!$B$4:$B$24,Database!I72) -> 1
... B77: 2070900000105 | C77: - | D77: - | E77: - | F77: =-SUMIF('1.1 FY2024'!$B:$B,Database!B77,'1.1 FY2024'!$F:$F) -> 0 | G77: =-SUMIF('1.2 FY2025'!$B:$B,Database!B77,'1.2 FY2025'!$F:$F) -> -276920 | H77: =-SUMIF('1.3 FY2026'!$B:$B,Database!B77,'1.3 FY2026'!$F:$F) -> -473575.46 | I77: Services | J77: =COUNTIF('P&L Model'!$B$4:$B$24,Database!I77) -> 1
B78: 20711000001900 | C78: - | D78: - | E78: - | F78: =-SUMIF('1.1 FY2024'!$B:$B,Database!B78,'1.1 FY2024'!$F:$F) -> 0 | G78: =-SUMIF('1.2 FY2025'!$B:$B,Database!B78,'1.2 FY2025'!$F:$F) -> 0 | H78: =-SUMIF('1.3 FY2026'!$B:$B,Database!B78,'1.3 FY2026'!$F:$F) -> 0 | J78: =COUNTIF('P&L Model'!$B$4:$B$24,Database!I78) -> 0
B79: 20712092001118 | C79: - | D79: - | E79: - | F79: =-SUMIF('1.1 FY2024'!$B:$B,Database!B79,'1.1 FY2024'!$F:$F) -> 0 | G79: =-SUMIF('1.2 FY2025'!$B:$B,Database!B79,'1.2 FY2025'!$F:$F) -> -23928.8 | H79: =-SUMIF('1.3 FY2026'!$B:$B,Database!B79,'1.3 FY2026'!$F:$F) -> 0 | I79: Other operating expenses | J79: =COUNTIF('P&L Model'!$B$4:$B$24,Database!I79) -> 1
B80: 2071220000111111 | C80: - | D80: - | E80: - | F80: =-SUMIF('1.1 FY2024'!$B:$B,Database!B80,'1.1 FY2024'!$F:$F) -> 0 | G80: =-SUMIF('1.2 FY2025'!$B:$B,Database!B80,'1.2 FY2025'!$F:$F) -> -308232 | H80: =-SUMIF('1.3 FY2026'!$B:$B,Database!B80,'1.3 FY2026'!$F:$F) -> 0 | I80: Extraordinary items | J80: =COUNTIF('P&L Model'!$B$4:$B$24,Database!I80) -> 1
B81: 207151100019 | C81: - | D81: - | E81: - | F81: =-SUMIF('1.1 FY2024'!$B:$B,Database!B81,'1.1 FY2024'!$F:$F) -> 0 | G81: =-SUMIF('1.2 FY2025'!$B:$B,Database!B81,'1.2 FY2025'!$F:$F) -> -13422.78 | H81: =-SUMIF('1.3 FY2026'!$B:$B,Database!B81,'1.3 FY2026'!$F:$F) -> 0 | I81: Other operating expenses | J81: =COUNTIF('P&L Model'!$B$4:$B$24,Database!I81) -> 1
B82: 2071511000111111 | C82: - | D82: - | E82: - | F82: =-SUMIF('1.1 FY2024'!$B:$B,Database!B82,'1.1 FY2024'!$F:$F) -> 0 | G82: =-SUMIF('1.2 FY2025'!$B:$B,Database!B82,'1.2 FY2025'!$F:$F) -> -4045.615 | H82: =-SUMIF('1.3 FY2026'!$B:$B,Database!B82,'1.3 FY2026'!$F:$F) -> 0 | I82: Other operating expenses | J82: =COUNTIF('P&L Model'!$B$4:$B$24,Database!I82) -> 1
B83: 2071910000111111 | C83: - | D83: - | E83: - | F83: =-SUMIF('1.1 FY2024'!$B:$B,Database!B83,'1.1 FY2024'!$F:$F) -> 0 | G83: =-SUMIF('1.2 FY2025'!$B:$B,Database!B83,'1.2 FY2025'!$F:$F) -> -49621.145 | H83: =-SUMIF('1.3 FY2026'!$B:$B,Database!B83,'1.3 FY2026'!$F:$F) -> 0 | I83: Other operating expenses | J83: =COUNTIF('P&L Model'!$B$4:$B$24,Database!I83) -> 1
B84: 207907000019 | C84: - | D84: - | E84: - | F84: =-SUMIF('1.1 FY2024'!$B:$B,Database!B84,'1.1 FY2024'!$F:$F) -> 0 | G84: =-SUMIF('1.2 FY2025'!$B:$B,Database!B84,'1.2 FY2025'!$F:$F) -> -85462.685 | H84: =-SUMIF('1.3 FY2026'!$B:$B,Database!B84,'1.3 FY2026'!$F:$F) -> 0 | I84: Extraordinary items | J84: =COUNTIF('P&L Model'!$B$4:$B$24,Database!I84) -> 1
B85: 207907000043 | C85: - | D85: - | E85: - | F85: =-SUMIF('1.1 FY2024'!$B:$B,Database!B85,'1.1 FY2024'!$F:$F) -> 0 | G85: =-SUMIF('1.2 FY2025'!$B:$B,Database!B85,'1.2 FY2025'!$F:$F) -> -11422.145 | H85: =-SUMIF('1.3 FY2026'!$B:$B,Database!B85,'1.3 FY2026'!$F:$F) -> 0 | I85: Extraordinary items | J85: =COUNTIF('P&L Model'!$B$4:$B$24,Database!I85) -> 1
B86: 20790700001924 | C86: - | D86: - | E86: - | F86: =-SUMIF('1.1 FY2024'!$B:$B,Database!B86,'1.1 FY2024'!$F:$F) -> 0 | G86: =-SUMIF('1.2 FY2025'!$B:$B,Database!B86,'1.2 FY2025'!$F:$F) -> -84438.865 | H86: =-SUMIF('1.3 FY2026'!$B:$B,Database!B86,'1.3 FY2026'!$F:$F) -> 0 | I86: Extraordinary items | J86: =COUNTIF('P&L Model'!$B$4:$B$24,Database!I86) -> 1
B87: 20790800001086 | C87: - | D87: - | E87: - | F87: =-SUMIF('1.1 FY2024'!$B:$B,Database!B87,'1.1 FY2024'!$F:$F) -> 0 | G87: =-SUMIF('1.2 FY2025'!$B:$B,Database!B87,'1.2 FY2025'!$F:$F) -> 0 | H87: =-SUMIF('1.3 FY2026'!$B:$B,Database!B87,'1.3 FY2026'!$F:$F) -> 0 | J87: =COUNTIF('P&L Model'!$B$4:$B$24,Database!I87) -> 0
B88: 20822800001086 | C88: - | D88: - | E88: - | F88: =-SUMIF('1.1 FY2024'!$B:$B,Database!B88,'1.1 FY2024'!$F:$F) -> 0 | G88: =-SUMIF('1.2 FY2025'!$B:$B,Database!B88,'1.2 FY2025'!$F:$F) -> 0 | H88: =-SUMIF('1.3 FY2026'!$B:$B,Database!B88,'1.3 FY2026'!$F:$F) -> 0 | I88: Financial items | J88: =COUNTIF('P&L Model'!$B$4:$B$24,Database!I88) -> 1
B89: 20822800001006 | C89: - | D89: - | E89: - | F89: =-SUMIF('1.1 FY2024'!$B:$B,Database!B89,'1.1 FY2024'!$F:$F) -> 0 | G89: =-SUMIF('1.2 FY2025'!$B:$B,Database!B89,'1.2 FY2025'!$F:$F) -> 6778.415 | H89: =-SUMIF('1.3 FY2026'!$B:$B,Database!B89,'1.3 FY2026'!$F:$F) -> 0 | I89: Financial items | J89: =COUNTIF('P&L Model'!$B$4:$B$24,Database!I89) -> 1
B90: 20822140001007 | C90: - | D90: - | E90: - | F90: =-SUMIF('1.1 FY2024'!$B:$B,Database!B90,'1.1 FY2024'!$F:$F) -> 0 | G90: =-SUMIF('1.2 FY2025'!$B:$B,Database!B90,'1.2 FY2025'!$F:$F) -> 0 | H90: =-SUMIF('1.3 FY2026'!$B:$B,Database!B90,'1.3 FY2026'!$F:$F) -> 0 | I90: Financial items | J90: =COUNTIF('P&L Model'!$B$4:$B$24,Database!I90) -> 1
B91: 2082214000111111 | C91: - | D91: - | E91: - | F91: =-SUMIF('1.1 FY2024'!$B:$B,Database!B91,'1.1 FY2024'!$F:$F) -> 0 | G91: =-SUMIF('1.2 FY2025'!$B:$B,Database!B91,'1.2 FY2025'!$F:$F) -> -1250.795 | H91: =-SUMIF('1.3 FY2026'!$B:$B,Database!B91,'1.3 FY2026'!$F:$F) -> -51.455 | I91: Financial items | J91: =COUNTIF('P&L Model'!$B$4:$B$24,Database!I91) -> 1
B92: 20821100001240 | C92: - | D92: - | E92: - | F92: =-SUMIF('1.1 FY2024'!$B:$B,Database!B92,'1.1 FY2024'!$F:$F) -> 0 | G92: =-SUMIF('1.2 FY2025'!$B:$B,Database!B92,'1.2 FY2025'!$F:$F) -> -4130000 | H92: =-SUMIF('1.3 FY2026'!$B:$B,Database!B92,'1.3 FY2026'!$F:$F) -> 0 | I92: Extraordinary items | J92: =COUNTIF('P&L Model'!$B$4:$B$24,Database!I92) -> 1
B93: 2091900000111101 | C93: - | D93: - | E93: - | F93: =-SUMIF('1.1 FY2024'!$B:$B,Database!B93,'1.1 FY2024'!$F:$F) -> 0 | G93: =-SUMIF('1.2 FY2025'!$B:$B,Database!B93,'1.2 FY2025'!$F:$F) -> 0 | H93: =-SUMIF('1.3 FY2026'!$B:$B,Database!B93,'1.3 FY2026'!$F:$F) -> 0 | J93: =COUNTIF('P&L Model'!$B$4:$B$24,Database!I93) -> 0
B94: 2111111999111101 | C94: - | D94: - | E94: - | F94: =-SUMIF('1.1 FY2024'!$B:$B,Database!B94,'1.1 FY2024'!$F:$F) -> 0 | G94: =-SUMIF('1.2 FY2025'!$B:$B,Database!B94,'1.2 FY2025'!$F:$F) -> -6073808.2 | H94: =-SUMIF('1.3 FY2026'!$B:$B,Database!B94,'1.3 FY2026'!$F:$F) -> 779290.48 | I94: Net Income | J94: =COUNTIF('P&L Model'!$B$4:$B$24,Database!I94) -> 1
B95: 2024020000111111 | C95: - | D95: - | E95: - | F95: =-SUMIF('1.1 FY2024'!$B:$B,Database!B95,'1.1 FY2024'!$F:$F) -> 0 | G95: =-SUMIF('1.2 FY2025'!$B:$B,Database!B95,'1.2 FY2025'!$F:$F) -> 0 | H95: =-SUMIF('1.3 FY2026'!$B:$B,Database!B95,'1.3 FY2026'!$F:$F) -> -13691.95 | I95: Other operating expenses | J95: =COUNTIF('P&L Model'!$B$4:$B$24,Database!I95) -> 1
B96: 20240900002185 | C96: - | D96: - | E96: - | F96: =-SUMIF('1.1 FY2024'!$B:$B,Database!B96,'1.1 FY2024'!$F:$F) -> 0 | G96: =-SUMIF('1.2 FY2025'!$B:$B,Database!B96,'1.2 FY2025'!$F:$F) -> 0 | H96: =-SUMIF('1.3 FY2026'!$B:$B,Database!B96,'1.3 FY2026'!$F:$F) -> -192017.14 | I96: Other operating expenses | J96: =COUNTIF('P&L Model'!$B$4:$B$24,Database!I96) -> 1
B97: 20240900002240 | C97: - | D97: - | E97: - | F97: =-SUMIF('1.1 FY2024'!$B:$B,Database!B97,'1.1 FY2024'!$F:$F) -> 0 | G97: =-SUMIF('1.2 FY2025'!$B:$B,Database!B97,'1.2 FY2025'!$F:$F) -> 0 | H97: =-SUMIF('1.3 FY2026'!$B:$B,Database!B97,'1.3 FY2026'!$F:$F) -> -375290.47 | I97: Other operating expenses | J97: =COUNTIF('P&L Model'!$B$4:$B$24,Database!I97) -> 1
B98: 202409000017000 | C98: - | D98: - | E98: - | F98: =-SUMIF('1.1 FY2024'!$B:$B,Database!B98,'1.1 FY2024'!$F:$F) -> 0 | G98: =-SUMIF('1.2 FY2025'!$B:$B,Database!B98,'1.2 FY2025'!$F:$F) -> 0 | H98: =-SUMIF('1.3 FY2026'!$B:$B,Database!B98,'1.3 FY2026'!$F:$F) -> -4920 | I98: Other operating expenses | J98: =COUNTIF('P&L Model'!$B$4:$B$24,Database!I98) -> 1
B99: 20604410001118 | C99: - | D99: - | E99: - | F99: =-SUMIF('1.1 FY2024'!$B:$B,Database!B99,'1.1 FY2024'!$F:$F) -> 0 | G99: =-SUMIF('1.2 FY2025'!$B:$B,Database!B99,'1.2 FY2025'!$F:$F) -> 0 | H99: =-SUMIF('1.3 FY2026'!$B:$B,Database!B99,'1.3 FY2026'!$F:$F) -> 0 | I99: Other operating expenses | J99: =COUNTIF('P&L Model'!$B$4:$B$24,Database!I99) -> 1
B100: 2060441000111111 | C100: - | D100: - | E100: - | F100: =-SUMIF('1.1 FY2024'!$B:$B,Database!B100,'1.1 FY2024'!$F:$F) -> 0 | G100: =-SUMIF('1.2 FY2025'!$B:$B,Database!B100,'1.2 FY2025'!$F:$F) -> 0 | H100: =-SUMIF('1.3 FY2026'!$B:$B,Database!B100,'1.3 FY2026'!$F:$F) -> 1252.837 | I100: Other operating expenses | J100: =COUNTIF('P&L Model'!$B$4:$B$24,Database!I100) -> 1
B101: 20690100001006 | C101: - | D101: - | E101: - | F101: =-SUMIF('1.1 FY2024'!$B:$B,Database!B101,'1.1 FY2024'!$F:$F) -> 0 | G101: =-SUMIF('1.2 FY2025'!$B:$B,Database!B101,'1.2 FY2025'!$F:$F) -> 0 | H101: =-SUMIF('1.3 FY2026'!$B:$B,Database!B101,'1.3 FY2026'!$F:$F) -> 0 | I101: Recharges | J101: =COUNTIF('P&L Model'!$B$4:$B$24,Database!I101) -> 1
B102: 2069020000111111 | C102: - | D102: - | E102: - | F102: =-SUMIF('1.1 FY2024'!$B:$B,Database!B102,'1.1 FY2024'!$F:$F) -> 0 | G102: =-SUMIF('1.2 FY2025'!$B:$B,Database!B102,'1.2 FY2025'!$F:$F) -> 0 | H102: =-SUMIF('1.3 FY2026'!$B:$B,Database!B102,'1.3 FY2026'!$F:$F) -> 61500 | I102: Other operating expenses | J102: =COUNTIF('P&L Model'!$B$4:$B$24,Database!I102) -> 1
B103: 2069980000105 | C103: - | D103: - | E103: - | F103: =-SUMIF('1.1 FY2024'!$B:$B,Database!B103,'1.1 FY2024'!$F:$F) -> 0 | G103: =-SUMIF('1.2 FY2025'!$B:$B,Database!B103,'1.2 FY2025'!$F:$F) -> 0 | H103: =-SUMIF('1.3 FY2026'!$B:$B,Database!B103,'1.3 FY2026'!$F:$F) -> 30913.426 | I103: Other income | J103: =COUNTIF('P&L Model'!$B$4:$B$24,Database!I103) -> 1
B104: 2070600000105 | C104: - | D104: - | E104: - | F104: =-SUMIF('1.1 FY2024'!$B:$B,Database!B104,'1.1 FY2024'!$F:$F) -> 0 | G104: =-SUMIF('1.2 FY2025'!$B:$B,Database!B104,'1.2 FY2025'!$F:$F) -> 0 | H104: =-SUMIF('1.3 FY2026'!$B:$B,Database!B104,'1.3 FY2026'!$F:$F) -> 1423120 | I104: Leasing | J104: =COUNTIF('P&L Model'!$B$4:$B$24,Database!I104) -> 1
B105: 207110000088 | C105: - | D105: - | E105: - | F105: =-SUMIF('1.1 FY2024'!$B:$B,Database!B105,'1.1 FY2024'!$F:$F) -> 0 | G105: =-SUMIF('1.2 FY2025'!$B:$B,Database!B105,'1.2 FY2025'!$F:$F) -> 0 | H105: =-SUMIF('1.3 FY2026'!$B:$B,Database!B105,'1.3 FY2026'!$F:$F) -> -584.66 | I105: Other operating expenses | J105: =COUNTIF('P&L Model'!$B$4:$B$24,Database!I105) -> 1
B106: 2071209100111111 | C106: - | D106: - | E106: - | F106: =-SUMIF('1.1 FY2024'!$B:$B,Database!B106,'1.1 FY2024'!$F:$F) -> 0 | G106: =-SUMIF('1.2 FY2025'!$B:$B,Database!B106,'1.2 FY2025'!$F:$F) -> 0 | H106: =-SUMIF('1.3 FY2026'!$B:$B,Database!B106,'1.3 FY2026'!$F:$F) -> -1353 | I106: Other operating expenses | J106: =COUNTIF('P&L Model'!$B$4:$B$24,Database!I106) -> 1
B107: 2082110000111101 | C107: - | D107: - | E107: - | F107: =-SUMIF('1.1 FY2024'!$B:$B,Database!B107,'1.1 FY2024'!$F:$F) -> 0 | G107: =-SUMIF('1.2 FY2025'!$B:$B,Database!B107,'1.2 FY2025'!$F:$F) -> 0 | H107: =-SUMIF('1.3 FY2026'!$B:$B,Database!B107,'1.3 FY2026'!$F:$F) -> 0 | J107: =COUNTIF('P&L Model'!$B$4:$B$24,Database!I107) -> 0
B108: 2111111997111101 | C108: - | D108: - | E108: - | F108: =-SUMIF('1.1 FY2024'!$B:$B,Database!B108,'1.1 FY2024'!$F:$F) -> 0 | G108: =-SUMIF('1.2 FY2025'!$B:$B,Database!B108,'1.2 FY2025'!$F:$F) -> 0 | H108: =-SUMIF('1.3 FY2026'!$B:$B,Database!B108,'1.3 FY2026'!$F:$F) -> 0 | J108: =COUNTIF('P&L Model'!$B$4:$B$24,Database!I108) -> 0

Sheet P&L Model
B1: P&L Statement
B3: EUR in millions | C3: FY24 | D3: FY25 | E3: FY26 | G3: Var% FY24-FY25 | H3: Var% FY25-FY26
B4: Net Sales | C4: =SUMIF(Database!$I:$I,'P&L Model'!B4,Database!$F:$F)/1000000 -> 14.500341 | D4: =SUMIF(Database!$I:$I,'P&L Model'!B4,Database!$G:$G)/1000000 -> 16.148295 | E4: =SUMIF(Database!$I:$I,'P&L Model'!B4,Database!$H:$H)/1000000 -> 15.047803 | G4: =(D4-C4)/C4*100 -> 11.364935 | H4: =(E4-D4)/D4*100 -> -6.8149134
B5: Other revenues | C5: =SUMIF(Database!$I:$I,'P&L Model'!B5,Database!$F:$F)/1000000 -> 4.7948562 | D5: =SUMIF(Database!$I:$I,'P&L Model'!B5,Database!$G:$G)/1000000 -> 6.9602176 | E5: =SUMIF(Database!$I:$I,'P&L Model'!B5,Database!$H:$H)/1000000 -> 6.3736175 | G5: =(D5-C5)/C5*100 -> 45.160092 | H5: =(E5-D5)/D5*100 -> -8.4278993
B6: Recharges | C6: =SUMIF(Database!$I:$I,'P&L Model'!B6,Database!$F:$F)/1000000 -> 3.2200543 | D6: =SUMIF(Database!$I:$I,'P&L Model'!B6,Database!$G:$G)/1000000 -> 2.924092 | E6: =SUMIF(Database!$I:$I,'P&L Model'!B6,Database!$H:$H)/1000000 -> 4.8931777 | G6: =(D6-C6)/C6*100 -> -9.1912196 | H6: =(E6-D6)/D6*100 -> 67.340075
B7: Total revenues | C7: =SUM(C4:C6) -> 22.515251 | D7: =SUM(D4:D6) -> 26.032605 | E7: =SUM(E4:E6) -> 26.314598 | G7: =(D7-C7)/C7*100 -> 15.622093 | H7: =(E7-D7)/D7*100 -> 1.083231
B8: Direct costs | C8: =SUMIF(Database!$I:$I,'P&L Model'!B8,Database!$F:$F)/1000000 -> -4.4289118 | D8: =SUMIF(Database!$I:$I,'P&L Model'!B8,Database!$G:$G)/1000000 -> -5.4631888 | E8: =SUMIF(Database!$I:$I,'P&L Model'!B8,Database!$H:$H)/1000000 -> -5.6741521 | G8: =(D8-C8)/C8*100 -> 23.352849 | H8: =(E8-D8)/D8*100 -> 3.8615404
B9: Gross margin | C9: =SUM(C7:C8) -> 18.08634 | D9: =SUM(D7:D8) -> 20.569416 | E9: =SUM(E7:E8) -> 20.640446 | G9: =(D9-C9)/C9*100 -> 13.729016 | H9: =(E9-D9)/D9*100 -> 0.34531858
B10: Other operating expenses | C10: =SUMIF(Database!$I:$I,'P&L Model'!B10,Database!$F:$F)/1000000 -> -3.396649 | D10: =SUMIF(Database!$I:$I,'P&L Model'!B10,Database!$G:$G)/1000000 -> -3.7048433 | E10: =SUMIF(Database!$I:$I,'P&L Model'!B10,Database!$H:$H)/1000000 -> -6.687483 | G10: =(D10-C10)/C10*100 -> 9.0734829 | H10: =(E10-D10)/D10*100 -> 80.5065
B11: Personnel expenses | C11: =SUMIF(Database!$I:$I,'P&L Model'!B11,Database!$F:$F)/1000000 -> -6.170739 | D11: =SUMIF(Database!$I:$I,'P&L Model'!B11,Database!$G:$G)/1000000 -> -8.0718589 | E11: =SUMIF(Database!$I:$I,'P&L Model'!B11,Database!$H:$H)/1000000 -> -5.8358882 | G11: =(D11-C11)/C11*100 -> 30.808626 | H11: =(E11-D11)/D11*100 -> -27.700816
B12: Leasing | C12: =SUMIF(Database!$I:$I,'P&L Model'!B12,Database!$F:$F)/1000000 -> -1.1274459 | D12: =SUMIF(Database!$I:$I,'P&L Model'!B12,Database!$G:$G)/1000000 -> -1.0553815 | E12: =SUMIF(Database!$I:$I,'P&L Model'!B12,Database!$H:$H)/1000000 -> 1.5960534 | G12: =(D12-C12)/C12*100 -> -6.3918277 | H12: =(E12-D12)/D12*100 -> -251.23
B13: Services | C13: =SUMIF(Database!$I:$I,'P&L Model'!B13,Database!$F:$F)/1000000 -> -2.5430882 | D13: =SUMIF(Database!$I:$I,'P&L Model'!B13,Database!$G:$G)/1000000 -> -1.8377863 | E13: =SUMIF(Database!$I:$I,'P&L Model'!B13,Database!$H:$H)/1000000 -> -1.9549839 | G13: =(D13-C13)/C13*100 -> -27.73407 | H13: =(E13-D13)/D13*100 -> 6.3771061
B14: Travel costs | C14: =SUMIF(Database!$I:$I,'P&L Model'!B14,Database!$F:$F)/1000000 -> -1.813525 | D14: =SUMIF(Database!$I:$I,'P&L Model'!B14,Database!$G:$G)/1000000 -> -2.3932592 | E14: =SUMIF(Database!$I:$I,'P&L Model'!B14,Database!$H:$H)/1000000 -> -2.5144319 | G14: =(D14-C14)/C14*100 -> 31.967256 | H14: =(E14-D14)/D14*100 -> 5.0630829
B15: Other income | C15: =SUMIF(Database!$I:$I,'P&L Model'!B15,Database!$F:$F)/1000000 -> 5.7222e-05 | D15: =SUMIF(Database!$I:$I,'P&L Model'!B15,Database!$G:$G)/1000000 -> -0.00735749 | E15: =SUMIF(Database!$I:$I,'P&L Model'!B15,Database!$H:$H)/1000000 -> 0.046785428 | G15: =(D15-C15)/C15*100 -> -12957.799 | H15: =(E15-D15)/D15*100 -> -735.88843
B16: Capitalized costs | C16: =SUMIF(Database!$I:$I,'P&L Model'!B16,Database!$F:$F)/1000000 -> 5.2683322 | D16: =SUMIF(Database!$I:$I,'P&L Model'!B16,Database!$G:$G)/1000000 -> 0.74482695 | E16: =SUMIF(Database!$I:$I,'P&L Model'!B16,Database!$H:$H)/1000000 -> 0 | G16: =(D16-C16)/C16*100 -> -85.862187 | H16: =(E16-D16)/D16*100 -> -100
B17: EBITDA | C17: =SUM(C9:C16) -> 8.303282 | D17: =SUM(D9:D16) -> 4.2437563 | E17: =SUM(E9:E16) -> 5.290498 | G17: =(D17-C17)/C17*100 -> -48.890615 | H17: =(E17-D17)/D17*100 -> 24.665452
B18: D&A | C18: =SUMIF(Database!$I:$I,'P&L Model'!B18,Database!$F:$F)/1000000 -> -2.0452435 | D18: =SUMIF(Database!$I:$I,'P&L Model'!B18,Database!$G:$G)/1000000 -> -2.0440058 | E18: =SUMIF(Database!$I:$I,'P&L Model'!B18,Database!$H:$H)/1000000 -> -1.8883615 | G18: =(D18-C18)/C18*100 -> -0.060515972 | H18: =(E18-D18)/D18*100 -> -7.6146702
B19: EBIT | C19: =SUM(C17:C18) -> 6.2580385 | D19: =SUM(D17:D18) -> 2.1997505 | E19: =SUM(E17:E18) -> 3.4021365 | G19: =(D19-C19)/C19*100 -> -64.849201 | H19: =(E19-D19)/D19*100 -> 54.660108
B20: Financial items | C20: =SUMIF(Database!$I:$I,'P&L Model'!B20,Database!$F:$F)/1000000 -> -2.8426924 | D20: =SUMIF(Database!$I:$I,'P&L Model'!B20,Database!$G:$G)/1000000 -> -2.7107469 | E20: =SUMIF(Database!$I:$I,'P&L Model'!B20,Database!$H:$H)/1000000 -> -2.2507078 | G20: =(D20-C20)/C20*100 -> -4.6415661 | H20: =(E20-D20)/D20*100 -> -16.970935
B21: Extraordinary items | C21: =SUMIF(Database!$I:$I,'P&L Model'!B21,Database!$F:$F)/1000000 -> -0.022763 | D21: =SUMIF(Database!$I:$I,'P&L Model'!B21,Database!$G:$G)/1000000 -> -4.5786198 | E21: =SUMIF(Database!$I:$I,'P&L Model'!B21,Database!$H:$H)/1000000 -> -0.007173196 | G21: =(D21-C21)/C21*100 -> 20014.307 | H21: =(E21-D21)/D21*100 -> -99.843333
B22: EBT | C22: =SUM(C19:C21) -> 3.3925831 | D22: =SUM(D19:D21) -> -5.0896162 | E22: =SUM(E19:E21) -> 1.1442555 | G22: =(D22-C22)/C22*100 -> -250.02186 | H22: =(E22-D22)/D22*100 -> -122.48216
B23: Taxes | C23: =SUMIF(Database!$I:$I,'P&L Model'!B23,Database!$F:$F)/1000000 -> -0.48846512 | D23: =SUMIF(Database!$I:$I,'P&L Model'!B23,Database!$G:$G)/1000000 -> -0.98419197 | E23: =SUMIF(Database!$I:$I,'P&L Model'!B23,Database!$H:$H)/1000000 -> -0.36496503 | G23: =(D23-C23)/C23*100 -> 101.48664 | H23: =(E23-D23)/D23*100 -> -62.917293
B24: Net Income | C24: =SUMIF(Database!$I:$I,'P&L Model'!B24,Database!$F:$F)/1000000 -> 2.904118 | D24: =SUMIF(Database!$I:$I,'P&L Model'!B24,Database!$G:$G)/1000000 -> -6.0738082 | E24: =SUMIF(Database!$I:$I,'P&L Model'!B24,Database!$H:$H)/1000000 -> 0.77929048 | G24: =(D24-C24)/C24*100 -> -309.14468 | H24: =(E24-D24)/D24*100 -> -112.83034
B26: KPIs
B27: GM% | C27: =C9/C7 -> 0.80329281 | D27: =D9/D7 -> 0.79014052 | E27: =E9/E7 -> 0.78437246
B28: EBITDA% | C28: =C17/C7 -> 0.36878478 | D28: =D17/D7 -> 0.16301697 | E28: =E17/E7 -> 0.20104803
B29: EBIT% | C29: =C19/C7 -> 0.27794664 | D29: =D19/D7 -> 0.084499823 | E29: =E19/E7 -> 0.12928704
B30: Net income | C30: =SUMIF('[1]2.1 Database'!$J:$J,'[1]2.2 P&L statement'!$B30,'[1]2.1 Database'!F:F)/1000000 -> #VALUE! | D30: =SUMIF('[1]2.1 Database'!$J:$J,'[1]2.2 P&L statement'!$B30,'[1]2.1 Database'!G:G)/1000000 -> #VALUE! | E30: =SUMIF('[1]2.1 Database'!$J:$J,'[1]2.2 P&L statement'!$B30,'[1]2.1 Database'!H:H)/1000000 -> #VALUE!
B31: Check | C31: =ROUND(C24+C30,9) -> #VALUE! | D31: =D24+D30 -> #VALUE! | E31: =E24+E30 -> #VALUE!

Sheet Charts --->
B13: Charts --->

Sheet Column Chart
B1: Column Chart
C3: FY24 | D3: FY25 | E3: FY26
B4: Net Sales | C4: ='P&L Model'!C4 -> 14.500341 | D4: ='P&L Model'!D4 -> 16.148295 | E4: ='P&L Model'!E4 -> 15.047803
B5: Other revenues | C5: ='P&L Model'!C5 -> 4.7948562 | D5: ='P&L Model'!D5 -> 6.9602176 | E5: ='P&L Model'!E5 -> 6.3736175
B6: Recharges | C6: ='P&L Model'!C6 -> 3.2200543 | D6: ='P&L Model'!D6 -> 2.924092 | E6: ='P&L Model'!E6 -> 4.8931777
B7: Gross Margin | C7: ='P&L Model'!C27 -> 0.80329281 | D7: ='P&L Model'!D27 -> 0.79014052 | E7: ='P&L Model'!E27 -> 0.78437246

Sheet Line chart
B1: Line chart
C3: FY2024 | D3: FY2025 | E3: FY2026
B4: Net Sales | C4: ='P&L Model'!C4 -> 14.500341 | D4: ='P&L Model'!D4 -> 16.148295 | E4: ='P&L Model'!E4 -> 15.047803
B5: Other revenues | C5: ='P&L Model'!C5 -> 4.7948562 | D5: ='P&L Model'!D5 -> 6.9602176 | E5: ='P&L Model'!E5 -> 6.3736175
B6: Recharges | C6: ='P&L Model'!C6 -> 3.2200543 | D6: ='P&L Model'!D6 -> 2.924092 | E6: ='P&L Model'!E6 -> 4.8931777

Sheet Stacked Column chart
B1: Stacked Column chart
B4: EBITDA FY 25 | C4: ='P&L Model'!D17 -> 4.2437563
B5: Changes in Revenue | C5: ='P&L Model'!E7-'P&L Model'!D7 -> 0.28199326
B6: Changes in Variable cost | C6: ='P&L Model'!E8-'P&L Model'!D8 -> -0.21096324
B7: Change in Opex | C7: {=SUM('P&L Model'!E10:E16-'P&L Model'!D10:D16)} -> 0.97571168
B8: EBITDA FY 26 | C8: ='P&L Model'!E17 -> 5.290498
